managingdifferentfunc/__init__.py
managingdifferentfunc/flight_ticketing_properties.py
flight_data_management-0.0.1.dist-info/LICENSE
flight_data_management-0.0.1.dist-info/METADATA
flight_data_management-0.0.1.dist-info/WHEEL
flight_data_management-0.0.1.dist-info/top_level.txt
flight_data_management-0.0.1.dist-info/RECORD
