Metadata-Version: 2.1
Name: flight_data_management
Version: 0.0.1
Summary: Utilities for managing flight data in a ticket booking system
Home-page: https://github.com/pypa/sampleproject
Author: Prakhar Singhwal
Author-email: x23285435@student.ncirl.ie
Classifier: Programming Language :: Python :: 3
Classifier: License :: OSI Approved :: MIT License
Classifier: Operating System :: OS Independent
Requires-Python: >=3.6
License-File: LICENSE
